pinexq/client/core/__init__.py
pinexq/client/core/api_event_manager.py
pinexq/client/core/base_relations.py
pinexq/client/core/enterapi.py
pinexq/client/core/exceptions.py
pinexq/client/core/hco/__init__.py
pinexq/client/core/hco/action_hco.py
pinexq/client/core/hco/action_with_parameters_hco.py
pinexq/client/core/hco/download_link_hco.py
pinexq/client/core/hco/hco_base.py
pinexq/client/core/hco/link_hco.py
pinexq/client/core/hco/unavailable.py
pinexq/client/core/hco/upload_action_hco.py
pinexq/client/core/http_headers.py
pinexq/client/core/media_types.py
pinexq/client/core/model/__init__.py
pinexq/client/core/model/error.py
pinexq/client/core/model/sirenmodels.py
pinexq/client/core/polling.py
pinexq/client/core/sirenaccess.py
pinexq/client/job_management/__init__.py
pinexq/client/job_management/enterjma.py
pinexq/client/job_management/hcos/__init__.py
pinexq/client/job_management/hcos/entrypoint_hco.py
pinexq/client/job_management/hcos/info_hco.py
pinexq/client/job_management/hcos/input_dataslot_hco.py
pinexq/client/job_management/hcos/job_hco.py
pinexq/client/job_management/hcos/job_query_result_hco.py
pinexq/client/job_management/hcos/job_used_tags_hco.py
pinexq/client/job_management/hcos/jobsroot_hco.py
pinexq/client/job_management/hcos/output_dataslot_hco.py
pinexq/client/job_management/hcos/processing_step_hco.py
pinexq/client/job_management/hcos/processing_step_used_tags_hco.py
pinexq/client/job_management/hcos/processingstep_query_result_hco.py
pinexq/client/job_management/hcos/processingsteproot_hco.py
pinexq/client/job_management/hcos/user_hco.py
pinexq/client/job_management/hcos/workdata_hco.py
pinexq/client/job_management/hcos/workdata_query_result_hco.py
pinexq/client/job_management/hcos/workdata_used_tags_query_result_hco.py
pinexq/client/job_management/hcos/workdataroot_hco.py
pinexq/client/job_management/known_relations.py
pinexq/client/job_management/model/__init__.py
pinexq/client/job_management/model/open_api_generated.py
pinexq_client-1.1.0.dist-info/WHEEL
pinexq_client-1.1.0.dist-info/METADATA
pinexq_client-1.1.0.dist-info/RECORD
