Metadata-Version: 2.3
Name: pinexq-client
Version: 1.1.0
Summary: A hypermedia-based client for the DataCybernetics PinexQ platform.
Author: Sebastian Höfer, Mathias Reichardt, Pratik Poudel
Author-email: Sebastian Höfer <hoefer@data-cybernetics.com>, Mathias Reichardt <reichardt@data-cybernetics.com>, Pratik Poudel <poudel@data-cybernetics.com>
License: MIT
Requires-Dist: pydantic>=2.1.0,<3.0.0
Requires-Dist: httpx>=0.25.0,<1.0.0
Requires-Dist: httpx-sse>=0.4.0
Requires-Dist: httpx-caching>=0.1a4
Maintainer: Mathias Reichardt, Sebastian Höfer, Carsten Blank
Maintainer-email: Mathias Reichardt <reichardt@data-cybernetics.com>, Sebastian Höfer <hoefer@data-cybernetics.com>, Carsten Blank <blank@data-cybernetics.com>
Requires-Python: >=3.11
